envbash/__init__.py
envbash/load.py
envbash/read.py
envbash-1.2.0.dist-info/LICENSE
envbash-1.2.0.dist-info/METADATA
envbash-1.2.0.dist-info/WHEEL
envbash-1.2.0.dist-info/top_level.txt
envbash-1.2.0.dist-info/RECORD
