Metadata-Version: 1.1
Name: envbash
Version: 1.2.0
Summary: Source env.bash script to update environment
Home-page: https://github.com/scampersand/envbash-python
Author: Aron Griffis
Author-email: aron@scampersand.com
License: MIT
Keywords: bash,environment,environ,env
Platform: UNKNOWN
Classifier: Development Status :: 5 - Production/Stable
Classifier: Intended Audience :: Developers
Classifier: License :: OSI Approved :: MIT License
Classifier: Programming Language :: Python
Classifier: Programming Language :: Python :: 2
Classifier: Programming Language :: Python :: 2.7
Classifier: Programming Language :: Python :: 3
Classifier: Programming Language :: Python :: 3.4
Classifier: Programming Language :: Python :: 3.5
Classifier: Programming Language :: Python :: 3.6
Classifier: Programming Language :: Python :: 3.7
